image_area_calculator/__init__.py
image_area_calculator/image_area_calculator.py
image_area_calculator-0.1.0.dist-info/LICENSE
image_area_calculator-0.1.0.dist-info/METADATA
image_area_calculator-0.1.0.dist-info/WHEEL
image_area_calculator-0.1.0.dist-info/entry_points.txt
image_area_calculator-0.1.0.dist-info/top_level.txt
image_area_calculator-0.1.0.dist-info/RECORD
