Metadata-Version: 2.1
Name: image_area_calculator
Version: 0.1.0
Summary: A package to calculate real-world areas of contours in images using a image of known length for scaling.
Home-page: https://github.com/clabe-wekesa/image-area-calculator
Author: Clabe Wekesa
Author-email: simiyu86wekesa@gmail.com
License: MIT
Keywords: image processing,contours,area calculation,opencv
Classifier: License :: OSI Approved :: MIT License
Classifier: Development Status :: 4 - Beta
Classifier: Intended Audience :: Developers
Classifier: Programming Language :: Python :: 3
Classifier: Programming Language :: Python :: 3.6
Classifier: Programming Language :: Python :: 3.7
Classifier: Programming Language :: Python :: 3.8
Classifier: Programming Language :: Python :: 3.9
Classifier: Programming Language :: Python :: 3.10
Classifier: Programming Language :: Python :: 3.11
Classifier: Operating System :: OS Independent
Requires-Python: >=3.6
License-File: LICENSE
Requires-Dist: Click
Requires-Dist: opencv-python
Requires-Dist: numpy
Requires-Dist: pdf2image
